[{"trial":0,"name":"optuna_000","weighting":"max_return","entry_rule":"mtt_or_rs","rs_threshold":95.0,"mtt_slope_months":5,"max_pool_months":12,"target_hit_multiplier":1.3,"stop_loss_pct":0.1,"reward_risk":4.0,"rebalance":"daily","lookback_days":252,"risk_free_rate":0.03,"min_target_upside":0.1,"exit_on_signal_loss":true,"allow_reentry":true,"run_id":"23327f39f06d","strategy_name":"optuna_000","final_log_wealth":0.4457959561515509,"total_return":0.5617327720559666,"cagr":0.2476132177669323,"annualized_volatility":0.4856049695246465,"sharpe":0.3788718619021595,"sortino":0.4220271212766791,"max_drawdown":0.3499226148493312,"calmar":0.7076227921809198,"realized_log_return":0.3320662147402934,"live_log_return":0.1137297414112575,"exposure_ratio":0.9657142857142856,"average_positions":6.91047619047619,"max_positions":18,"turnover_events":2311,"trade_count":406,"win_rate":0.458128078817734,"target_hit_rate":0.0541871921182266,"stop_loss_hit_rate":0.0862068965517241,"average_holding_days":11.65024630541872,"objective":0.4457959561515509,"open_position_count":15,"status":"ok"},{"trial":1,"name":"optuna_001","weighting":"min_var","entry_rule":"mtt_or_rs","rs_threshold":80.0,"mtt_slope_months":3,"max_pool_months":6,"target_hit_multiplier":1.5,"stop_loss_pct":0.08,"reward_risk":4.0,"rebalance":"weekly","lookback_days":378,"risk_free_rate":0.03,"min_target_upside":0.0,"exit_on_signal_loss":true,"allow_reentry":true,"run_id":"69ddba57e685","strategy_name":"optuna_001","final_log_wealth":0.4723061348321655,"total_return":0.6036882534208916,"cagr":0.2641353069248937,"annualized_volatility":0.2873764291359769,"sharpe":0.6844922713768024,"sortino":0.8579570443035096,"max_drawdown":0.2321907613171955,"calmar":1.1375788830980178,"realized_log_return":0.3719183404279086,"live_log_return":0.1003877944042569,"exposure_ratio":0.9447619047619048,"average_positions":5.396190476190476,"max_positions":13,"turnover_events":676,"trade_count":171,"win_rate":0.3859649122807017,"target_hit_rate":0.1578947368421052,"stop_loss_hit_rate":0.4152046783625731,"average_holding_days":21.976608187134502,"objective":0.4723061348321655,"open_position_count":11,"status":"ok"},{"trial":2,"name":"optuna_002","weighting":"max_return","entry_rule":"mtt_and_rs","rs_threshold":60.0,"mtt_slope_months":2,"max_pool_months":12,"target_hit_multiplier":1.2,"stop_loss_pct":0.1,"reward_risk":2.0,"rebalance":"daily","lookback_days":504,"risk_free_rate":0.03,"min_target_upside":0.2,"exit_on_signal_loss":true,"allow_reentry":true,"run_id":"fad0941ceca4","strategy_name":"optuna_002","final_log_wealth":0.0454287106373904,"total_return":0.046476399319205,"cagr":0.0228006652874588,"annualized_volatility":0.4893599507813344,"sharpe":-0.0167447681016176,"sortino":-0.0195184308535643,"max_drawdown":0.5622662980768658,"calmar":0.0405513639452418,"realized_log_return":0.031096137987799,"live_log_return":0.0143325726495913,"exposure_ratio":0.9542857142857144,"average_positions":5.428571428571429,"max_positions":13,"turnover_events":1965,"trade_count":420,"win_rate":0.469047619047619,"target_hit_rate":0.1261904761904762,"stop_loss_hit_rate":0.1214285714285714,"average_holding_days":9.290476190476191,"objective":0.0454287106373904,"open_position_count":11,"status":"ok"},{"trial":3,"name":"optuna_003","weighting":"sortino","entry_rule":"hybrid_score","rs_threshold":80.0,"mtt_slope_months":5,"max_pool_months":3,"target_hit_multiplier":1.2,"stop_loss_pct":0.08,"reward_risk":2.0,"rebalance":"weekly","lookback_days":378,"risk_free_rate":0.03,"min_target_upside":0.1,"exit_on_signal_loss":true,"allow_reentry":true,"run_id":"47a318767795","strategy_name":"optuna_003","final_log_wealth":0.6081819379015128,"total_return":0.8370884200029629,"cagr":0.3523158267735238,"annualized_volatility":0.3073687426767038,"sharpe":0.852159942848275,"sortino":0.9463576036031304,"max_drawdown":0.2940226507559086,"calmar":1.1982608342171874,"realized_log_return":0.593508022021202,"live_log_return":0.0146739158803107,"exposure_ratio":0.6895238095238095,"average_positions":2.4514285714285715,"max_positions":12,"turnover_events":356,"trade_count":120,"win_rate":0.4333333333333333,"target_hit_rate":0.2333333333333333,"stop_loss_hit_rate":0.3583333333333333,"average_holding_days":15.258333333333333,"objective":0.6081819379015128,"open_position_count":4,"status":"ok"},{"trial":4,"name":"optuna_004","weighting":"calmar","entry_rule":"hybrid_score","rs_threshold":65.0,"mtt_slope_months":4,"max_pool_months":3,"target_hit_multiplier":1.3,"stop_loss_pct":0.12,"reward_risk":2.0,"rebalance":"weekly","lookback_days":504,"risk_free_rate":0.03,"min_target_upside":0.1,"exit_on_signal_loss":true,"allow_reentry":true,"run_id":"5b6610dacaa2","strategy_name":"optuna_004","final_log_wealth":0.2766966893761383,"total_return":0.3187663145337434,"cagr":0.1471888730234012,"annualized_volatility":0.2922625299901354,"sharpe":0.3517878631380378,"sortino":0.3740955965765831,"max_drawdown":0.3615274391548262,"calmar":0.407130571796977,"realized_log_return":0.2620227734958277,"live_log_return":0.0146739158803105,"exposure_ratio":0.7390476190476191,"average_positions":3.382857142857143,"max_positions":13,"turnover_events":413,"trade_count":121,"win_rate":0.4793388429752066,"target_hit_rate":0.140495867768595,"stop_loss_hit_rate":0.1900826446280991,"average_holding_days":20.677685950413224,"objective":0.2766966893761383,"open_position_count":4,"status":"ok"},{"trial":5,"name":"optuna_005","weighting":"min_var","entry_rule":"mtt_or_rs","rs_threshold":95.0,"mtt_slope_months":5,"max_pool_months":12,"target_hit_multiplier":1.5,"stop_loss_pct":0.06,"reward_risk":3.0,"rebalance":"biweekly","lookback_days":378,"risk_free_rate":0.03,"min_target_upside":0.1,"exit_on_signal_loss":true,"allow_reentry":true,"run_id":"478c2786df73","strategy_name":"optuna_005","final_log_wealth":0.2107594383268766,"total_return":0.2346153182083736,"cagr":0.1102577936037179,"annualized_volatility":0.2137351025333062,"sharpe":0.3329566812068752,"sortino":0.3739743868326679,"max_drawdown":0.3823478240428317,"calmar":0.2883703964570398,"realized_log_return":0.1932205593018687,"live_log_return":0.0175388790250078,"exposure_ratio":0.8914285714285715,"average_positions":5.295238095238095,"max_positions":15,"turnover_events":536,"trade_count":203,"win_rate":0.4285714285714285,"target_hit_rate":0.2857142857142857,"stop_loss_hit_rate":0.4926108374384236,"average_holding_days":18.448275862068964,"objective":0.2107594383268766,"open_position_count":8,"status":"ok"},{"trial":6,"name":"optuna_006","weighting":"sharpe","entry_rule":"hybrid_score","rs_threshold":75.0,"mtt_slope_months":5,"max_pool_months":6,"target_hit_multiplier":1.2,"stop_loss_pct":0.08,"reward_risk":4.0,"rebalance":"daily","lookback_days":378,"risk_free_rate":0.03,"min_target_upside":0.0,"exit_on_signal_loss":true,"allow_reentry":true,"run_id":"37e44d325e34","strategy_name":"optuna_006","final_log_wealth":0.6552119704941047,"total_return":0.9255506340398104,"cagr":0.3842491223488404,"annualized_volatility":0.3314208295473866,"sharpe":0.8584304922104843,"sortino":1.1846028021215855,"max_drawdown":0.2967009374007431,"calmar":1.2950721548609374,"realized_log_return":0.5679770603729606,"live_log_return":0.0872349101211441,"exposure_ratio":0.9714285714285714,"average_positions":5.308571428571429,"max_positions":13,"turnover_events":2239,"trade_count":428,"win_rate":0.4719626168224299,"target_hit_rate":0.0490654205607476,"stop_loss_hit_rate":0.1939252336448598,"average_holding_days":8.69392523364486,"objective":0.6552119704941047,"open_position_count":11,"status":"ok"},{"trial":7,"name":"optuna_007","weighting":"sortino","entry_rule":"target_only","rs_threshold":80.0,"mtt_slope_months":5,"max_pool_months":3,"target_hit_multiplier":1.1,"stop_loss_pct":0.12,"reward_risk":4.0,"rebalance":"monthly","lookback_days":504,"risk_free_rate":0.03,"min_target_upside":0.2,"exit_on_signal_loss":true,"allow_reentry":true,"run_id":"89e792ab46c7","strategy_name":"optuna_007","final_log_wealth":-0.0639855959196604,"total_return":-0.0619814892725903,"cagr":-0.0312548660481504,"annualized_volatility":0.2356836503744481,"sharpe":-0.2576041483784626,"sortino":-0.243463314125361,"max_drawdown":0.3385891666287599,"calmar":-0.0923091141968498,"realized_log_return":-0.0639855959196605,"live_log_return":1.1102230246251563e-16,"exposure_ratio":0.6819047619047619,"average_positions":4.855238095238096,"max_positions":17,"turnover_events":241,"trade_count":87,"win_rate":0.5632183908045977,"target_hit_rate":0.057471264367816,"stop_loss_hit_rate":0.3218390804597701,"average_holding_days":41.03448275862069,"objective":-0.0639855959196604,"open_position_count":0,"status":"ok"}]
